{
    "ㄆㄚ": "2:9.3",
    "ㄆㄚˊ": "2:10.1",
    "ㄆㄚˇ": "2:11.0",
    "ㄆㄚˋ": "2:11.8",
    "ㄆㄛ": "2:12.5",
    "ㄆㄛˊ": "2:13.4",
    "ㄆㄛˇ": "2:14.3",
    "ㄆㄛˋ": "2:15.2",
    "ㄆㄞ": "2:16.1",
    "ㄆㄞˊ": "2:17.1",
    "ㄆㄞˇ": "2:18.1",
    "ㄆㄞˋ": "2:18.7",
    "ㄆㄟ": "2:19.6",
    "ㄆㄟˊ": "2:20.6",
    "ㄆㄟˇ": "2:21.4",
    "ㄆㄟˋ": "2:22.2",
    "ㄆㄠ": "2:23.0",
    "ㄆㄠˊ": "2:23.9",
    "ㄆㄠˇ": "2:24.8",
    "ㄆㄠˋ": "2:25.5",
    "ㄆㄡ": "2:26.3",
    "ㄆㄡˊ": "2:27.3",
    "ㄆㄡˇ": "2:28.0",
    "ㄆㄡˋ": "2:28.8",
    "ㄆㄢ": "2:29.7",
    "ㄆㄢˊ": "2:30.4",
    "ㄆㄢˇ": "2:31.3",
    "ㄆㄢˋ": "2:32.1",
    "ㄆㄣ": "2:33.0",
    "ㄆㄣˊ": "2:33.7",
    "ㄆㄣˇ": "2:34.6",
    "ㄆㄣˋ": "2:35.4",
    "ㄆㄤ": "2:36.2",
    "ㄆㄤˊ": "2:36.9",
    "ㄆㄤˇ": "2:37.8",
    "ㄆㄤˋ": "2:38.6",
    "ㄆㄥ": "2:39.4",
    "ㄆㄥˊ": "2:40.3",
    "ㄆㄥˇ": "2:41.2",
    "ㄆㄥˋ": "2:42.0",
    "ㄆㄧ": "2:42.8",
    "ㄆㄧˊ": "2:43.7",
    "ㄆㄧˇ": "2:44.5",
    "ㄆㄧˋ": "2:45.2",
    "ㄆㄧㄝ": "2:46.1",
    "ㄆㄧㄝˊ": "2:47.0",
    "ㄆㄧㄝˇ": "2:47.8",
    "ㄆㄧㄝˋ": "2:48.4",
    "ㄆㄧㄠ": "2:49.3",
    "ㄆㄧㄠˊ": "2:50.2",
    "ㄆㄧㄠˇ": "2:51.1",
    "ㄆㄧㄠˋ": "2:51.9",
    "ㄆㄧㄢ": "2:52.8",
    "ㄆㄧㄢˊ": "2:53.7",
    "ㄆㄧㄢˇ": "2:54.5",
    "ㄆㄧㄢˋ": "2:55.3",
    "ㄆㄧㄣ": "2:56.1",
    "ㄆㄧㄣˊ": "2:57.0",
    "ㄆㄧㄣˇ": "2:57.9",
    "ㄆㄧㄣˋ": "2:58.6",
    "ㄆㄧㄥ": "2:59.4",
    "ㄆㄧㄥˊ": "3:0.4",
    "ㄆㄧㄥˇ": "3:1.1",
    "ㄆㄧㄥˋ": "3:1.9",
    "ㄆㄨ": "3:2.8",
    "ㄆㄨˊ": "3:3.7",
    "ㄆㄨˇ": "3:4.5",
    "ㄆㄨˋ": "3:5.3"
}